modmux/__init__.py
modmux/__main__.py
modmux/_log.py
modmux/cache.py
modmux/cli.py
modmux/client.py
modmux/models.py
modmux/modmux_errors.py
modmux/providers/__init__.py
modmux/providers/_base.py
modmux/providers/curseforge.py
modmux/providers/modio.py
modmux/providers/modrinth.py
modmux/providers/nexusmods.py
modmux/providers/steam.py
modmux/providers/wube.py
modmux/utils/__init__.py
modmux/utils/discovery.py
modmux/utils/urls.py
modmux-0.2.2.dist-info/METADATA
modmux-0.2.2.dist-info/WHEEL
modmux-0.2.2.dist-info/entry_points.txt
modmux-0.2.2.dist-info/licenses/LICENSE
modmux-0.2.2.dist-info/RECORD
