Metadata-Version: 2.4
Name: modmux
Version: 0.2.2
Summary: Single interface for several game mod portals
Author: APasz
License: MIT
License-File: LICENSE
Requires-Python: >=3.13
Requires-Dist: aiolimiter<2,>=1.2
Requires-Dist: httpx<1,>=0.28
Requires-Dist: pydantic<3,>=2
